StrTokenizer/__init__.py
StrTokenizer/tokenizer.py
StrTokenizer-1.1.0.dist-info/LICENSE.md
StrTokenizer-1.1.0.dist-info/METADATA
StrTokenizer-1.1.0.dist-info/WHEEL
StrTokenizer-1.1.0.dist-info/top_level.txt
StrTokenizer-1.1.0.dist-info/RECORD
