Metadata-Version: 2.1
Name: StrTokenizer
Version: 1.1.0
Summary: A Python equivalent of Java's StringTokenizer with some added functionality
Home-page: https://github.com/CyberPokemon/StrTokenizer.git
Author: Imon Mallik
Author-email: imoncoding@gmail.com
Keywords: string tokenizer split parse
Classifier: Programming Language :: Python :: 3
Classifier: License :: OSI Approved :: MIT License
Classifier: Operating System :: OS Independent
Classifier: Development Status :: 5 - Production/Stable
Classifier: Intended Audience :: Developers
Classifier: Topic :: Software Development :: Libraries :: Python Modules
Requires-Python: >=3.6
License-File: LICENSE.md
